gleetex/__init__.py
gleetex/__main__.py
gleetex/cachedconverter.py
gleetex/caching.py
gleetex/htmlhandling.py
gleetex/image.py
gleetex/pandoc.py
gleetex/parser.py
gleetex/typesetting.py
gleetex/unicode.py
GladTeX-3.1.0.dist-info/COPYING
GladTeX-3.1.0.dist-info/METADATA
GladTeX-3.1.0.dist-info/WHEEL
GladTeX-3.1.0.dist-info/entry_points.txt
GladTeX-3.1.0.dist-info/top_level.txt
GladTeX-3.1.0.dist-info/RECORD
