Metadata-Version: 2.1
Name: GladTeX
Version: 3.1.0
Summary: Formula typesetting for the web using LaTeX
Home-page: https://humenda.github.io/GladTeX
Author: Sebastian Humenda
Author-email: shumenda@gmx.de
License: LGPL3.0
Platform: UNKNOWN
